tap_clickhouse/__init__.py
tap_clickhouse/client.py
tap_clickhouse/tap.py
akurdyukov_tap_clickhouse-0.0.1.dist-info/LICENSE
akurdyukov_tap_clickhouse-0.0.1.dist-info/METADATA
akurdyukov_tap_clickhouse-0.0.1.dist-info/WHEEL
akurdyukov_tap_clickhouse-0.0.1.dist-info/entry_points.txt
akurdyukov_tap_clickhouse-0.0.1.dist-info/RECORD
