Metadata-Version: 2.1
Name: akurdyukov-tap-clickhouse
Version: 0.0.1
Summary: `tap-clickhouse` is a Singer tap for ClickHouse, built with the Meltano Singer SDK.
License: Apache-2.0
Keywords: ELT,ClickHouse
Author: Alik Kurdyukov
Author-email: alik@kurdyukov.com
Requires-Python: >=3.7.1,<4
Classifier: License :: OSI Approved :: Apache Software License
Classifier: Programming Language :: Python :: 3
Classifier: Programming Language :: Python :: 3.8
Classifier: Programming Language :: Python :: 3.9
Classifier: Programming Language :: Python :: 3.10
Classifier: Programming Language :: Python :: 3.11
Provides-Extra: s3
Requires-Dist: clickhouse_sqlalchemy (>=0.2.5)
Requires-Dist: fs-s3fs (>=1.1.1,<1.2.0) ; extra == "s3"
Requires-Dist: singer-sdk (>=0.33.0,<0.34.0)
